aiohttpapi/__init__.py
aiohttpapi-0.0.1.dist-info/LICENSE
aiohttpapi-0.0.1.dist-info/WHEEL
aiohttpapi-0.0.1.dist-info/METADATA
aiohttpapi-0.0.1.dist-info/RECORD
